uncalibrated_linearsvc/__init__.py
uncalibrated_linearsvc-0.0.1.dist-info/licenses/LICENSE
uncalibrated_linearsvc-0.0.1.dist-info/METADATA
uncalibrated_linearsvc-0.0.1.dist-info/WHEEL
uncalibrated_linearsvc-0.0.1.dist-info/top_level.txt
uncalibrated_linearsvc-0.0.1.dist-info/RECORD
